powerflex_logging_utilities/VERSION
powerflex_logging_utilities/__init__.py
powerflex_logging_utilities/default_log_format.py
powerflex_logging_utilities/forbid_toplevel_logging.py
powerflex_logging_utilities/init_loggers.py
powerflex_logging_utilities/json_formatter.py
powerflex_logging_utilities/log_slow_callbacks.py
powerflex_logging_utilities/py.typed
powerflex_logging_utilities/trace_logger.py
powerflex_logging_utilities/log_level_listener/__init__.py
powerflex_logging_utilities/log_level_listener/format_exception.py
powerflex_logging_utilities/log_level_listener/nats.py
powerflex_logging_utilities-1.3.1.dist-info/LICENSE
powerflex_logging_utilities-1.3.1.dist-info/METADATA
powerflex_logging_utilities-1.3.1.dist-info/WHEEL
powerflex_logging_utilities-1.3.1.dist-info/top_level.txt
powerflex_logging_utilities-1.3.1.dist-info/zip-safe
powerflex_logging_utilities-1.3.1.dist-info/RECORD
