Metadata-Version: 2.1
Name: powerflex-logging-utilities
Version: 1.3.1
Summary: Helpful code for logging in Python
Home-page: https://github.com/edf-re/powerflex_logging_utilities_py
License: MIT License
Project-URL: Issue Tracker, https://github.com/edf-re/powerflex_logging_utilities_py/issues
Keywords: NATS,NATS request,aiodebug,async,JSON logging
Classifier: Intended Audience :: Developers
Classifier: Operating System :: Unix
Classifier: Operating System :: POSIX
Classifier: Operating System :: Microsoft :: Windows
Classifier: Programming Language :: Python
Classifier: Programming Language :: Python :: 3
Classifier: Programming Language :: Python :: 3.8
Classifier: Programming Language :: Python :: 3.9
Classifier: Programming Language :: Python :: 3.10
Classifier: Programming Language :: Python :: 3.11
Classifier: Programming Language :: Python :: Implementation :: CPython
Classifier: Programming Language :: Python :: Implementation :: PyPy
Classifier: Topic :: Utilities
Requires-Python: >2.7, !=3.0.*, !=3.1.*, !=3.2.*, !=3.3.*, !=3.4.*, !=3.5.*, !=3.6.*, !=3.7.*
License-File: LICENSE
Requires-Dist: aiodebug >=2.3.0
Requires-Dist: python-json-logger >=2.0.0
Provides-Extra: nats-and-pydantic
Requires-Dist: nats-py >=2 ; extra == 'nats-and-pydantic'
Requires-Dist: pydantic ; extra == 'nats-and-pydantic'
Provides-Extra: nats-and-pydantic2
Requires-Dist: nats-py >=2 ; extra == 'nats-and-pydantic2'
Requires-Dist: pydantic >=2 ; extra == 'nats-and-pydantic2'
Requires-Dist: pydantic-settings >=2 ; extra == 'nats-and-pydantic2'
Provides-Extra: pydantic
Requires-Dist: pydantic >=1.9 ; extra == 'pydantic'
Provides-Extra: pydantic2
Requires-Dist: pydantic >=2 ; extra == 'pydantic2'
Requires-Dist: pydantic-settings >=2 ; extra == 'pydantic2'
